json_schematizer/__about__.py
json_schematizer/__init__.py
json_schematizer/codecs.py
json_schematizer-0.0.1.dist-info/METADATA
json_schematizer-0.0.1.dist-info/WHEEL
json_schematizer-0.0.1.dist-info/licenses/LICENSE.txt
json_schematizer-0.0.1.dist-info/RECORD
